setup.py
mbs/__init__.py
mbs/app.py
mbs/auth.py
mbs/blueprint.py
mbs/client.py
mbs/datamanager.py
mbs/errors.py
mbs/settings.py
mbs/views.py
mbs/scripts/__init__.py
mbs/scripts/run.py
mbs/tests/__init__.py
mbs/tests/test_server.py
mbs/tests/test_settings.py
mbs/tests/test_views.py
multiuserblazeserver.egg-info/PKG-INFO
multiuserblazeserver.egg-info/SOURCES.txt
multiuserblazeserver.egg-info/dependency_links.txt
multiuserblazeserver.egg-info/not-zip-safe
multiuserblazeserver.egg-info/requires.txt
multiuserblazeserver.egg-info/top_level.txt