Metadata-Version: 1.0
Name: multiuserblazeserver
Version: 0.2.1
Summary: Multi User Blaze Server
Home-page: http://github.com/ContinuumIO/multiuserblazeserver
Author: Continuum Analytics
Author-email: UNKNOWN
License: New BSD
Platform: UNKNOWN
